ahkunwrapped/__init__.py
ahkunwrapped/autohotkey.py
ahkunwrapped/py.typed
ahkunwrapped/lib/AutoHotkey/AutoHotkey.exe
ahkunwrapped/lib/AutoHotkey/NOTICE
ahkunwrapped-2.2.1.dist-info/LICENSE
ahkunwrapped-2.2.1.dist-info/METADATA
ahkunwrapped-2.2.1.dist-info/NOTICE
ahkunwrapped-2.2.1.dist-info/WHEEL
ahkunwrapped-2.2.1.dist-info/top_level.txt
ahkunwrapped-2.2.1.dist-info/RECORD
