Metadata-Version: 2.1
Name: ahkunwrapped
Version: 2.2.1
Summary: Bundled and bridged AutoHotkey for full native code execution from Python.
Home-page: https://github.com/CodeOptimist/ahkunwrapped
Author: Christopher Galpin
License: UNKNOWN
Project-URL: Discord, https://discord.gg/Uz5rnWUkrV
Keywords: AutoHotkey,AHK
Platform: UNKNOWN
Classifier: License :: OSI Approved :: GNU Affero General Public License v3 or later (AGPLv3+)
Classifier: Development Status :: 5 - Production/Stable
Classifier: Operating System :: Microsoft :: Windows :: Windows Vista
Classifier: Operating System :: Microsoft :: Windows :: Windows 7
Classifier: Operating System :: Microsoft :: Windows :: Windows 8
Classifier: Operating System :: Microsoft :: Windows :: Windows 8.1
Classifier: Operating System :: Microsoft :: Windows :: Windows 10
Classifier: Programming Language :: Python :: 3 :: Only
Classifier: Programming Language :: Python :: 3.6
Classifier: Programming Language :: Python :: 3.7
Classifier: Programming Language :: Python :: 3.8
Classifier: Programming Language :: Python :: 3.9
Classifier: Programming Language :: Python :: 3.10
Classifier: Environment :: Win32 (MS Windows)
Classifier: Topic :: Software Development :: Libraries :: Python Modules
Requires-Python: >=3.6
License-File: LICENSE
License-File: NOTICE
Requires-Dist: pywin32 (>=227) ; platform_system == "Windows"
